civicrmapi/__init__.py
civicrmapi/__version__.py
civicrmapi/base.py
civicrmapi/console.py
civicrmapi/errors.py
civicrmapi/rest.py
civicrmapi/v3.py
civicrmapi/v4.py
civicrmapi/v3/__init__.py
civicrmapi/v4/__init__.py
civicrmapi/v4/group.py
civicrmapi-0.1.dev2.dist-info/LICENCE
civicrmapi-0.1.dev2.dist-info/METADATA
civicrmapi-0.1.dev2.dist-info/WHEEL
civicrmapi-0.1.dev2.dist-info/top_level.txt
civicrmapi-0.1.dev2.dist-info/zip-safe
civicrmapi-0.1.dev2.dist-info/RECORD
