Metadata-Version: 2.1
Name: civicrmapi
Version: 0.1.dev2
Summary: Connect with the CiviCRM APIv4.
Home-page: https://github.com/thomst/civicrmapi
Author: Thomas Leichtfuß
Author-email: thomas.leichtfuss@posteo.de
License: BSD License
Platform: OS Independent
Classifier: Development Status :: 3 - Alpha
Classifier: Intended Audience :: Developers
Classifier: License :: OSI Approved :: BSD License
Classifier: Operating System :: OS Independent
Classifier: Programming Language :: Python
Classifier: Programming Language :: Python :: 3
Classifier: Programming Language :: Python :: 3.6
Classifier: Programming Language :: Python :: 3.7
Classifier: Programming Language :: Python :: 3.8
Classifier: Programming Language :: Python :: 3.9
Classifier: Programming Language :: Python :: 3.10
Classifier: Programming Language :: Python :: 3.11
Classifier: Topic :: Software Development
Classifier: Topic :: Software Development :: Libraries
License-File: LICENCE
Requires-Dist: requests
Requires-Dist: invoke
